chaudhary/__init__.py
chaudhary/settings.py
chaudhary/urls.py
chaudhary/wsgi.py
chaudhary-1.0.dist-info/DESCRIPTION.rst
chaudhary-1.0.dist-info/METADATA
chaudhary-1.0.dist-info/RECORD
chaudhary-1.0.dist-info/WHEEL
chaudhary-1.0.dist-info/metadata.json
chaudhary-1.0.dist-info/top_level.txt
