Metadata-Version: 2.0
Name: chaudhary
Version: 1.0
Summary: farzi vala app
Home-page: UNKNOWN
Author: Achintya Ranjan Chaudhary
Author-email: achintyac77@gmail.com
License: MIT
Platform: UNKNOWN
